{
  "generatedAt": "2025-12-03T12:39:28.534Z",
  "count": 142,
  "users": [
    {
      "username": "angeliina_rokes",
      "href": "https://www.instagram.com/_u/angeliina_rokes"
    },
    {
      "username": "anna_boldyy",
      "href": "https://www.instagram.com/_u/anna_boldyy"
    },
    {
      "username": "books_lisss",
      "href": "https://www.instagram.com/_u/books_lisss"
    },
    {
      "username": "romanova___mari",
      "href": "https://www.instagram.com/_u/romanova___mari"
    },
    {
      "username": "khamidovanz",
      "href": "https://www.instagram.com/_u/khamidovanz"
    },
    {
      "username": "angelliice",
      "href": "https://www.instagram.com/_u/angelliice"
    },
    {
      "username": "aly.vinaaa",
      "href": "https://www.instagram.com/_u/aly.vinaaa"
    },
    {
      "username": "quin.star21",
      "href": "https://www.instagram.com/_u/quin.star21"
    },
    {
      "username": "ezik_mari",
      "href": "https://www.instagram.com/_u/ezik_mari"
    },
    {
      "username": "marrgulichka",
      "href": "https://www.instagram.com/_u/marrgulichka"
    },
    {
      "username": "valeriya_kek_art",
      "href": "https://www.instagram.com/_u/valeriya_kek_art"
    },
    {
      "username": "yan4ik_baldina",
      "href": "https://www.instagram.com/_u/yan4ik_baldina"
    },
    {
      "username": "irishadovgaliuk",
      "href": "https://www.instagram.com/_u/irishadovgaliuk"
    },
    {
      "username": "polyakova_ann_",
      "href": "https://www.instagram.com/_u/polyakova_ann_"
    },
    {
      "username": "nails_bro_spb",
      "href": "https://www.instagram.com/_u/nails_bro_spb"
    },
    {
      "username": "aniuta9596",
      "href": "https://www.instagram.com/_u/aniuta9596"
    },
    {
      "username": "shkavrova_",
      "href": "https://www.instagram.com/_u/shkavrova_"
    },
    {
      "username": "veronika__universe",
      "href": "https://www.instagram.com/_u/veronika__universe"
    },
    {
      "username": "teterina0811",
      "href": "https://www.instagram.com/_u/teterina0811"
    },
    {
      "username": "lenormanistka",
      "href": "https://www.instagram.com/_u/lenormanistka"
    },
    {
      "username": "keratina_alevtina",
      "href": "https://www.instagram.com/_u/keratina_alevtina"
    },
    {
      "username": "rashitova.ju",
      "href": "https://www.instagram.com/_u/rashitova.ju"
    },
    {
      "username": "aisylu__photo",
      "href": "https://www.instagram.com/_u/aisylu__photo"
    },
    {
      "username": "dszhka",
      "href": "https://www.instagram.com/_u/dszhka"
    },
    {
      "username": "nadiivleva",
      "href": "https://www.instagram.com/_u/nadiivleva"
    },
    {
      "username": "photo_lilith_",
      "href": "https://www.instagram.com/_u/photo_lilith_"
    },
    {
      "username": "lenaa.sergeevna",
      "href": "https://www.instagram.com/_u/lenaa.sergeevna"
    },
    {
      "username": "sidelnikova91",
      "href": "https://www.instagram.com/_u/sidelnikova91"
    },
    {
      "username": "alieva261023",
      "href": "https://www.instagram.com/_u/alieva261023"
    },
    {
      "username": "zvani_zavtrak",
      "href": "https://www.instagram.com/_u/zvani_zavtrak"
    },
    {
      "username": "julia2604ru",
      "href": "https://www.instagram.com/_u/julia2604ru"
    },
    {
      "username": "nastya_mirari",
      "href": "https://www.instagram.com/_u/nastya_mirari"
    },
    {
      "username": "ekaterina_karanadze",
      "href": "https://www.instagram.com/_u/ekaterina_karanadze"
    },
    {
      "username": "chernoskutovatb",
      "href": "https://www.instagram.com/_u/chernoskutovatb"
    },
    {
      "username": "miiamur01",
      "href": "https://www.instagram.com/_u/miiamur01"
    },
    {
      "username": "lina_.vak",
      "href": "https://www.instagram.com/_u/lina_.vak"
    },
    {
      "username": "dasha_vavi_lova",
      "href": "https://www.instagram.com/_u/dasha_vavi_lova"
    },
    {
      "username": "gveraone",
      "href": "https://www.instagram.com/_u/gveraone"
    },
    {
      "username": "nastya___stylist",
      "href": "https://www.instagram.com/_u/nastya___stylist"
    },
    {
      "username": "shrbn_f",
      "href": "https://www.instagram.com/_u/shrbn_f"
    },
    {
      "username": "angelinnix",
      "href": "https://www.instagram.com/_u/angelinnix"
    },
    {
      "username": "pavllorya.desserts",
      "href": "https://www.instagram.com/_u/pavllorya.desserts"
    },
    {
      "username": "tam.000001",
      "href": "https://www.instagram.com/_u/tam.000001"
    },
    {
      "username": "_s_kseniya_v",
      "href": "https://www.instagram.com/_u/_s_kseniya_v"
    },
    {
      "username": "anna__lovemakeup",
      "href": "https://www.instagram.com/_u/anna__lovemakeup"
    },
    {
      "username": "darya.bersenevva",
      "href": "https://www.instagram.com/_u/darya.bersenevva"
    },
    {
      "username": "sivakova.1317",
      "href": "https://www.instagram.com/_u/sivakova.1317"
    },
    {
      "username": "djulies.blog",
      "href": "https://www.instagram.com/_u/djulies.blog"
    },
    {
      "username": "gubina.ss",
      "href": "https://www.instagram.com/_u/gubina.ss"
    },
    {
      "username": "dominika_pavlovna",
      "href": "https://www.instagram.com/_u/dominika_pavlovna"
    },
    {
      "username": "karinessa__2206",
      "href": "https://www.instagram.com/_u/karinessa__2206"
    },
    {
      "username": "men_vipshoping_26",
      "href": "https://www.instagram.com/_u/men_vipshoping_26"
    },
    {
      "username": "danniiiiele",
      "href": "https://www.instagram.com/_u/danniiiiele"
    },
    {
      "username": "strangervinyyl",
      "href": "https://www.instagram.com/_u/strangervinyyl"
    },
    {
      "username": "dasha_lisovenko",
      "href": "https://www.instagram.com/_u/dasha_lisovenko"
    },
    {
      "username": "yuli.and.slav",
      "href": "https://www.instagram.com/_u/yuli.and.slav"
    },
    {
      "username": "ai_gromova",
      "href": "https://www.instagram.com/_u/ai_gromova"
    },
    {
      "username": "nelmua_",
      "href": "https://www.instagram.com/_u/nelmua_"
    },
    {
      "username": "vvv.emelyanova",
      "href": "https://www.instagram.com/_u/vvv.emelyanova"
    },
    {
      "username": "n.y.u.t.s",
      "href": "https://www.instagram.com/_u/n.y.u.t.s"
    },
    {
      "username": "belaayyaa",
      "href": "https://www.instagram.com/_u/belaayyaa"
    },
    {
      "username": "lenara.wow",
      "href": "https://www.instagram.com/_u/lenara.wow"
    },
    {
      "username": "levnkova",
      "href": "https://www.instagram.com/_u/levnkova"
    },
    {
      "username": "mari_korotovskih",
      "href": "https://www.instagram.com/_u/mari_korotovskih"
    },
    {
      "username": "yulia_sivaya",
      "href": "https://www.instagram.com/_u/yulia_sivaya"
    },
    {
      "username": "elstolba",
      "href": "https://www.instagram.com/_u/elstolba"
    },
    {
      "username": "_lidos__",
      "href": "https://www.instagram.com/_u/_lidos__"
    },
    {
      "username": "smirnovshina00",
      "href": "https://www.instagram.com/_u/smirnovshina00"
    },
    {
      "username": "plusekontent",
      "href": "https://www.instagram.com/_u/plusekontent"
    },
    {
      "username": "melomanka_mi",
      "href": "https://www.instagram.com/_u/melomanka_mi"
    },
    {
      "username": "dari_pole_dance",
      "href": "https://www.instagram.com/_u/dari_pole_dance"
    },
    {
      "username": "nk_kochetkova",
      "href": "https://www.instagram.com/_u/nk_kochetkova"
    },
    {
      "username": "galinaoffix",
      "href": "https://www.instagram.com/_u/galinaoffix"
    },
    {
      "username": "reviving_rose2304",
      "href": "https://www.instagram.com/_u/reviving_rose2304"
    },
    {
      "username": "koliiis_s",
      "href": "https://www.instagram.com/_u/koliiis_s"
    },
    {
      "username": "daria_dalakyan999",
      "href": "https://www.instagram.com/_u/daria_dalakyan999"
    },
    {
      "username": "wow_decor_krd",
      "href": "https://www.instagram.com/_u/wow_decor_krd"
    },
    {
      "username": "avv.roni",
      "href": "https://www.instagram.com/_u/avv.roni"
    },
    {
      "username": "pronko.psy",
      "href": "https://www.instagram.com/_u/pronko.psy"
    },
    {
      "username": "keti_mmm",
      "href": "https://www.instagram.com/_u/keti_mmm"
    },
    {
      "username": "alikova_permanent",
      "href": "https://www.instagram.com/_u/alikova_permanent"
    },
    {
      "username": "svetlana_dutchak_",
      "href": "https://www.instagram.com/_u/svetlana_dutchak_"
    },
    {
      "username": "tvoytarologiny",
      "href": "https://www.instagram.com/_u/tvoytarologiny"
    },
    {
      "username": "diya__dii",
      "href": "https://www.instagram.com/_u/diya__dii"
    },
    {
      "username": "elena_k07",
      "href": "https://www.instagram.com/_u/elena_k07"
    },
    {
      "username": "sanechka.s_",
      "href": "https://www.instagram.com/_u/sanechka.s_"
    },
    {
      "username": "yuliaa_kn",
      "href": "https://www.instagram.com/_u/yuliaa_kn"
    },
    {
      "username": "regina_kovrigina",
      "href": "https://www.instagram.com/_u/regina_kovrigina"
    },
    {
      "username": "ayshe_ka777",
      "href": "https://www.instagram.com/_u/ayshe_ka777"
    },
    {
      "username": "krisblog_i",
      "href": "https://www.instagram.com/_u/krisblog_i"
    },
    {
      "username": "anastasiabrotko",
      "href": "https://www.instagram.com/_u/anastasiabrotko"
    },
    {
      "username": "cool_3tarot",
      "href": "https://www.instagram.com/_u/cool_3tarot"
    },
    {
      "username": "polia.belia",
      "href": "https://www.instagram.com/_u/polia.belia"
    },
    {
      "username": "eliavino",
      "href": "https://www.instagram.com/_u/eliavino"
    },
    {
      "username": "psihologiya.deneg",
      "href": "https://www.instagram.com/_u/psihologiya.deneg"
    },
    {
      "username": "svi.kk",
      "href": "https://www.instagram.com/_u/svi.kk"
    },
    {
      "username": "alineesssa",
      "href": "https://www.instagram.com/_u/alineesssa"
    },
    {
      "username": "viuggova",
      "href": "https://www.instagram.com/_u/viuggova"
    },
    {
      "username": "lera._brows",
      "href": "https://www.instagram.com/_u/lera._brows"
    },
    {
      "username": "slav_a2614",
      "href": "https://www.instagram.com/_u/slav_a2614"
    },
    {
      "username": "riadeair",
      "href": "https://www.instagram.com/_u/riadeair"
    },
    {
      "username": "__frolova.d__",
      "href": "https://www.instagram.com/_u/__frolova.d__"
    },
    {
      "username": "poypae.e",
      "href": "https://www.instagram.com/_u/poypae.e"
    },
    {
      "username": "nosovpartner",
      "href": "https://www.instagram.com/_u/nosovpartner"
    },
    {
      "username": "olesia.pohabova",
      "href": "https://www.instagram.com/_u/olesia.pohabova"
    },
    {
      "username": "make_me_cry001",
      "href": "https://www.instagram.com/_u/make_me_cry001"
    },
    {
      "username": "stasy.taro_",
      "href": "https://www.instagram.com/_u/stasy.taro_"
    },
    {
      "username": "fotomusicbox",
      "href": "https://www.instagram.com/_u/fotomusicbox"
    },
    {
      "username": "german_barukh",
      "href": "https://www.instagram.com/_u/german_barukh"
    },
    {
      "username": "_mitroshaa_",
      "href": "https://www.instagram.com/_u/_mitroshaa_"
    },
    {
      "username": "veralilas_game",
      "href": "https://www.instagram.com/_u/veralilas_game"
    },
    {
      "username": "mednaya_babochka",
      "href": "https://www.instagram.com/_u/mednaya_babochka"
    },
    {
      "username": "amaliya12341",
      "href": "https://www.instagram.com/_u/amaliya12341"
    },
    {
      "username": "katea.sinitsa",
      "href": "https://www.instagram.com/_u/katea.sinitsa"
    },
    {
      "username": "11alissaaa11",
      "href": "https://www.instagram.com/_u/11alissaaa11"
    },
    {
      "username": "la_room_rnd",
      "href": "https://www.instagram.com/_u/la_room_rnd"
    },
    {
      "username": "patimat.izaeva",
      "href": "https://www.instagram.com/_u/patimat.izaeva"
    },
    {
      "username": "tarolog.dar",
      "href": "https://www.instagram.com/_u/tarolog.dar"
    },
    {
      "username": "ismillona",
      "href": "https://www.instagram.com/_u/ismillona"
    },
    {
      "username": "artukova_28__",
      "href": "https://www.instagram.com/_u/artukova_28__"
    },
    {
      "username": "prom.ts6",
      "href": "https://www.instagram.com/_u/prom.ts6"
    },
    {
      "username": "letta_22.12",
      "href": "https://www.instagram.com/_u/letta_22.12"
    },
    {
      "username": "pershina13",
      "href": "https://www.instagram.com/_u/pershina13"
    },
    {
      "username": "fitmamaspain",
      "href": "https://www.instagram.com/_u/fitmamaspain"
    },
    {
      "username": "yavorskaya_v_",
      "href": "https://www.instagram.com/_u/yavorskaya_v_"
    },
    {
      "username": "matrix22mari",
      "href": "https://www.instagram.com/_u/matrix22mari"
    },
    {
      "username": "_little__lark__",
      "href": "https://www.instagram.com/_u/_little__lark__"
    },
    {
      "username": "privalochka_m",
      "href": "https://www.instagram.com/_u/privalochka_m"
    },
    {
      "username": "k.kemilisss",
      "href": "https://www.instagram.com/_u/k.kemilisss"
    },
    {
      "username": "adriana.yakovleva",
      "href": "https://www.instagram.com/_u/adriana.yakovleva"
    },
    {
      "username": "vasiliiik_",
      "href": "https://www.instagram.com/_u/vasiliiik_"
    },
    {
      "username": "blacktarohell",
      "href": "https://www.instagram.com/_u/blacktarohell"
    },
    {
      "username": "kulikova01",
      "href": "https://www.instagram.com/_u/kulikova01"
    },
    {
      "username": "anna_yasiulevich24",
      "href": "https://www.instagram.com/_u/anna_yasiulevich24"
    },
    {
      "username": "yulia.purpur",
      "href": "https://www.instagram.com/_u/yulia.purpur"
    },
    {
      "username": "elen.yuzhikova",
      "href": "https://www.instagram.com/_u/elen.yuzhikova"
    },
    {
      "username": "evkamalina",
      "href": "https://www.instagram.com/_u/evkamalina"
    },
    {
      "username": "neurograph_mikheeva",
      "href": "https://www.instagram.com/_u/neurograph_mikheeva"
    },
    {
      "username": "solovyshka.ly",
      "href": "https://www.instagram.com/_u/solovyshka.ly"
    },
    {
      "username": "__deleted__bhiebeagaddcfbdcc",
      "href": "https://www.instagram.com/_u/__deleted__bhiebeagaddcfbdcc"
    },
    {
      "username": "stanovvaya",
      "href": "https://www.instagram.com/_u/stanovvaya"
    },
    {
      "username": "lisa_hkkk",
      "href": "https://www.instagram.com/_u/lisa_hkkk"
    }
  ]
}